README.rst
ewave.py
ewave-1.0.10.dist-info/METADATA
ewave-1.0.10.dist-info/WHEEL
ewave-1.0.10.dist-info/RECORD
