Metadata-Version: 2.4
Name: ewave
Version: 1.0.10
Summary: Extended WAVE I/O
Project-URL: Homepage, https://github.com/melizalab/py-ewave
Author-email: C Daniel Meliza <dan@meliza.org>
Maintainer-email: C Daniel Meliza <dan@meliza.org>
License: Python Software Foundation License
Keywords: data format,sound file
Classifier: Development Status :: 5 - Production/Stable
Classifier: Environment :: Console
Classifier: Intended Audience :: Developers
Classifier: License :: OSI Approved :: Python Software Foundation License
Classifier: Natural Language :: English
Classifier: Operating System :: MacOS :: MacOS X
Classifier: Operating System :: Microsoft :: Windows
Classifier: Operating System :: POSIX :: Linux
Classifier: Operating System :: Unix
Classifier: Programming Language :: Python
Classifier: Programming Language :: Python :: 3.7
Classifier: Programming Language :: Python :: 3.8
Classifier: Programming Language :: Python :: 3.9
Classifier: Programming Language :: Python :: 3.10
Classifier: Programming Language :: Python :: 3.11
Classifier: Programming Language :: Python :: 3.12
Classifier: Programming Language :: Python :: Implementation :: CPython
Classifier: Programming Language :: Python :: Implementation :: PyPy
Classifier: Topic :: Multimedia :: Sound/Audio :: Conversion
Requires-Python: >=3.7
Requires-Dist: numpy>=1.21.6; python_version == '3.7'
Requires-Dist: numpy>=1.23.2; python_version == '3.10'
Requires-Dist: numpy>=1.23.2; python_version == '3.8'
Requires-Dist: numpy>=1.23.2; python_version == '3.9'
Requires-Dist: numpy>=1.24.0; python_version == '3.11'
Requires-Dist: numpy>=1.26.0; python_version == '3.12'
